{
  "collectionName": "components_modules_gift_finders",
  "info": {
    "displayName": "gift_finder",
    "icon": "apple-alt",
    "description": ""
  },
  "options": {},
  "attributes": {
    "cta_age": {
      "type": "string"
    },
    "default_url": {
      "type": "string"
    },
    "image_desktop": {
      "type": "media",
      "multiple": false,
      "required": false,
      "allowedTypes": [
        "images"
      ]
    },
    "cta_theme": {
      "type": "string"
    },
    "image_alt": {
      "type": "string"
    },
    "subheading": {
      "type": "string"
    },
    "heading": {
      "type": "string"
    },
    "square_view": {
      "type": "boolean"
    },
    "elements": {
      "displayName": "gift_finder_themes",
      "type": "component",
      "repeatable": true,
      "component": "elements.gift-finder-themes"
    },
    "hr": {
      "type": "boolean"
    },
    "cta_price": {
      "type": "string"
    },
    "image_mobile": {
      "allowedTypes": [
        "images"
      ],
      "type": "media",
      "multiple": false
    }
  }
}
